LICENSE
README.md
pyproject.toml
setup.py
tronpy/__init__.py
tronpy/abi.py
tronpy/async_contract.py
tronpy/async_tron.py
tronpy/contract.py
tronpy/defaults.py
tronpy/exceptions.py
tronpy/tron.py
tronpy/keys/__init__.py
tronpy/providers/__init__.py
tronpy/providers/async_http.py
tronpy/providers/http.py
tronpy_chek.egg-info/PKG-INFO
tronpy_chek.egg-info/SOURCES.txt
tronpy_chek.egg-info/dependency_links.txt
tronpy_chek.egg-info/requires.txt
tronpy_chek.egg-info/top_level.txt